[{"WARD":"7","total":1896,"closed":740,"open":1156,"pct_closed":0.3902953586,"median_ttc_hours":46.3002777778,"mean_ttc_hours":51.4654523273,"median_open_age_hours":264.2053960875},{"WARD":"8","total":1605,"closed":244,"open":1361,"pct_closed":0.1520249221,"median_ttc_hours":125.6022222222,"mean_ttc_hours":110.3016871585,"median_open_age_hours":320.4523405319},{"WARD":"4","total":1405,"closed":441,"open":964,"pct_closed":0.3138790036,"median_ttc_hours":37.84,"mean_ttc_hours":42.4341710758,"median_open_age_hours":295.4281738653},{"WARD":"5","total":1321,"closed":737,"open":584,"pct_closed":0.5579106737,"median_ttc_hours":23.7497222222,"mean_ttc_hours":34.8415878939,"median_open_age_hours":217.9348405319},{"WARD":"6","total":1026,"closed":288,"open":738,"pct_closed":0.2807017544,"median_ttc_hours":40.8716666667,"mean_ttc_hours":38.6545968364,"median_open_age_hours":318.2603960875},{"WARD":"3","total":952,"closed":101,"open":851,"pct_closed":0.106092437,"median_ttc_hours":55.6880555556,"mean_ttc_hours":50.9310671067,"median_open_age_hours":341.1181738653},{"WARD":"2","total":929,"closed":52,"open":877,"pct_closed":0.0559741658,"median_ttc_hours":21.1793055556,"mean_ttc_hours":43.8598023504,"median_open_age_hours":337.7548405319},{"WARD":"1","total":846,"closed":81,"open":765,"pct_closed":0.0957446809,"median_ttc_hours":114.5463888889,"mean_ttc_hours":101.5936934156,"median_open_age_hours":340.4659516431}]