[{"WARD":"7","total":1742,"closed":740,"open":1002,"pct_closed":0.4247990815,"median_ttc_hours":46.3002777778,"mean_ttc_hours":51.4654523273,"median_open_age_hours":165.6550218444},{"WARD":"8","total":1484,"closed":244,"open":1240,"pct_closed":0.1644204852,"median_ttc_hours":125.6022222222,"mean_ttc_hours":110.3016871585,"median_open_age_hours":189.8489107333},{"WARD":"4","total":1289,"closed":441,"open":848,"pct_closed":0.3421256788,"median_ttc_hours":37.84,"mean_ttc_hours":42.4341710758,"median_open_age_hours":171.3173829556},{"WARD":"5","total":1199,"closed":737,"open":462,"pct_closed":0.6146788991,"median_ttc_hours":23.7497222222,"mean_ttc_hours":34.8415878939,"median_open_age_hours":87.5162718444},{"WARD":"6","total":961,"closed":288,"open":673,"pct_closed":0.2996878252,"median_ttc_hours":40.8716666667,"mean_ttc_hours":38.6545968364,"median_open_age_hours":184.9289107333},{"WARD":"3","total":870,"closed":101,"open":769,"pct_closed":0.116091954,"median_ttc_hours":55.6880555556,"mean_ttc_hours":50.9310671067,"median_open_age_hours":196.4894662889},{"WARD":"2","total":847,"closed":52,"open":795,"pct_closed":0.0613931523,"median_ttc_hours":21.1793055556,"mean_ttc_hours":43.8598023504,"median_open_age_hours":193.8950218444},{"WARD":"1","total":793,"closed":81,"open":712,"pct_closed":0.1021437579,"median_ttc_hours":114.5463888889,"mean_ttc_hours":101.5936934156,"median_open_age_hours":193.9489107333}]