[{"WARD":"7","total":1908,"closed":742,"open":1166,"pct_closed":0.3888888889,"median_ttc_hours":46.3597222222,"mean_ttc_hours":52.100289383,"median_open_age_hours":423.6099030806},{"WARD":"8","total":1617,"closed":248,"open":1369,"pct_closed":0.1533704391,"median_ttc_hours":126.1804166667,"mean_ttc_hours":116.5158501344,"median_open_age_hours":483.8854586361},{"WARD":"4","total":1425,"closed":769,"open":656,"pct_closed":0.5396491228,"median_ttc_hours":64.3158333333,"mean_ttc_hours":227.4017493859,"median_open_age_hours":405.5740697472},{"WARD":"5","total":1328,"closed":736,"open":592,"pct_closed":0.5542168675,"median_ttc_hours":23.7311111111,"mean_ttc_hours":34.6882997434,"median_open_age_hours":381.1182364139},{"WARD":"6","total":1036,"closed":287,"open":749,"pct_closed":0.277027027,"median_ttc_hours":40.8477777778,"mean_ttc_hours":39.6703977933,"median_open_age_hours":480.8396253028},{"WARD":"3","total":975,"closed":154,"open":821,"pct_closed":0.1579487179,"median_ttc_hours":64.69,"mean_ttc_hours":210.091976912,"median_open_age_hours":501.989347525},{"WARD":"2","total":945,"closed":52,"open":893,"pct_closed":0.055026455,"median_ttc_hours":21.1793055556,"mean_ttc_hours":43.8598023504,"median_open_age_hours":501.2829586361},{"WARD":"1","total":855,"closed":81,"open":774,"pct_closed":0.0947368421,"median_ttc_hours":114.5463888889,"mean_ttc_hours":101.5936934156,"median_open_age_hours":503.3939308583}]