[{"WARD":"7","total":1280,"closed":526,"open":754,"pct_closed":0.4109375,"median_ttc_hours":39.0897222222,"mean_ttc_hours":40.5148700887,"median_open_age_hours":62.7348040028},{"WARD":"8","total":1098,"closed":105,"open":993,"pct_closed":0.0956284153,"median_ttc_hours":53.7444444444,"mean_ttc_hours":46.0960026455,"median_open_age_hours":79.6699428917},{"WARD":"4","total":935,"closed":390,"open":545,"pct_closed":0.4171122995,"median_ttc_hours":33.5409722222,"mean_ttc_hours":37.1663824786,"median_open_age_hours":75.560776225},{"WARD":"5","total":837,"closed":578,"open":259,"pct_closed":0.6905615293,"median_ttc_hours":19.2413888889,"mean_ttc_hours":23.1694088812,"median_open_age_hours":50.3599428917},{"WARD":"6","total":720,"closed":283,"open":437,"pct_closed":0.3930555556,"median_ttc_hours":40.8294444444,"mean_ttc_hours":39.6098782882,"median_open_age_hours":74.3138317806},{"WARD":"3","total":666,"closed":99,"open":567,"pct_closed":0.1486486486,"median_ttc_hours":55.5725,"mean_ttc_hours":51.9909848485,"median_open_age_hours":79.7168873361},{"WARD":"2","total":626,"closed":47,"open":579,"pct_closed":0.0750798722,"median_ttc_hours":21.0763888889,"mean_ttc_hours":33.3365130024,"median_open_age_hours":77.6166095583},{"WARD":"1","total":589,"closed":38,"open":551,"pct_closed":0.064516129,"median_ttc_hours":58.8802777778,"mean_ttc_hours":57.224627193,"median_open_age_hours":78.3466095583}]